MANIFEST.in
README.rst
setup.py
django_pretty_times.egg-info/PKG-INFO
django_pretty_times.egg-info/SOURCES.txt
django_pretty_times.egg-info/dependency_links.txt
django_pretty_times.egg-info/not-zip-safe
django_pretty_times.egg-info/requires.txt
django_pretty_times.egg-info/top_level.txt
pretty_times/__init__.py
pretty_times/models.py
pretty_times/pretty.py
pretty_times/tests.py
pretty_times/locale/en/LC_MESSAGES/django.mo
pretty_times/locale/en/LC_MESSAGES/django.po
pretty_times/locale/fr/LC_MESSAGES/django.mo
pretty_times/locale/fr/LC_MESSAGES/django.po
pretty_times/templatetags/__init__.py
pretty_times/templatetags/prettytimes_tags.py
requirements/base.txt
requirements/test.txt