Metadata-Version: 1.1
Name: django-pretty-times
Version: 0.2.0
Summary: pretty_times provides django template helpers for the py-pretty library.
Home-page: http://github.com/imtapps/django-pretty-times
Author: imtapps
Author-email: imtapps@apps-system.com
License: UNKNOWN
Platform: UNKNOWN
Classifier: Development Status :: 3 - Alpha
Classifier: Environment :: Web Environment
Classifier: Framework :: Django
Classifier: Intended Audience :: Developers
Classifier: License :: OSI Approved :: BSD License
Classifier: Operating System :: OS Independent
Classifier: Programming Language :: Python
Classifier: Topic :: Software Development
Classifier: Topic :: Software Development :: Libraries :: Application Frameworks
